noonutil/__init__.py
noonutil/main.py
noonutil-0.2.dist-info/METADATA
noonutil-0.2.dist-info/WHEEL
noonutil-0.2.dist-info/top_level.txt
noonutil-0.2.dist-info/RECORD
