Metadata-Version: 2.4
Name: noonutil
Version: 0.2
Summary: A security research PoC package.
Requires-Dist: requests
Dynamic: requires-dist
Dynamic: summary
